credential_manager_mcp/__init__.py
credential_manager_mcp/server.py
credential_manager_mcp-1.0.2.dist-info/METADATA
credential_manager_mcp-1.0.2.dist-info/WHEEL
credential_manager_mcp-1.0.2.dist-info/entry_points.txt
credential_manager_mcp-1.0.2.dist-info/licenses/LICENSE
credential_manager_mcp-1.0.2.dist-info/RECORD
