Metadata-Version: 2.4
Name: credential-manager-mcp
Version: 1.0.2
Summary: A FastMCP server for securely managing API credentials locally
Project-URL: Homepage, https://github.com/mclamee/credential-manager-mcp
Project-URL: Repository, https://github.com/mclamee/credential-manager-mcp
Project-URL: Issues, https://github.com/mclamee/credential-manager-mcp/issues
Author-email: William Zhang <mclamee@yeah.net>
License: MIT
License-File: LICENSE
Keywords: api,credentials,fastmcp,mcp,model-context-protocol
Classifier: Development Status :: 4 - Beta
Classifier: Intended Audience :: Developers
Classifier: License :: OSI Approved :: MIT License
Classifier: Programming Language :: Python :: 3
Classifier: Programming Language :: Python :: 3.13
Classifier: Topic :: Security
Classifier: Topic :: Software Development :: Libraries :: Python Modules
Classifier: Topic :: System :: Systems Administration
Requires-Python: >=3.13
Requires-Dist: fastmcp>=2.8.0
Requires-Dist: pydantic>=2.11.0
